yiedl/__init__.py
yiedl/contracts.py
yiedl/delegate.py
yiedl/settings.py
yiedl/submitter.py
yiedl/tools.py
yiedl/json_interfaces/Competition.json
yiedl/json_interfaces/Token.json
yiedl_ai-0.2.4.dist-info/licenses/LICENSE
yiedl_ai-0.2.4.dist-info/METADATA
yiedl_ai-0.2.4.dist-info/WHEEL
yiedl_ai-0.2.4.dist-info/top_level.txt
yiedl_ai-0.2.4.dist-info/RECORD
