Metadata-Version: 2.4
Name: yiedl-ai
Version: 0.2.4
Summary: Programmaticaly interact with the yiedl machine learning competition
License: MIT License
Project-URL: Repository, https://github.com/rocketcapital-ai/competition_submission
Project-URL: Documentation, https://docs.yiedl.ai/rci-competition
Project-URL: Changelog, https://github.com/rocketcapital-ai/competition_submission/CHANGELOG.md
Project-URL: Releases, https://github.com/rocketcapital-ai/competition_submission/releases
Project-URL: Discord, https://discord.com/invite/r6NbnCSrzn
Requires-Python: >=3.11
License-File: LICENSE
Requires-Dist: base58>=2.1.1
Requires-Dist: requests>=2.32.3
Requires-Dist: web3>=7.7.0
Requires-Dist: pandas>=2.2.3
Requires-Dist: tqdm>=4.67.1
Requires-Dist: pyarrow>=23.0.0
Requires-Dist: fastparquet>=2025.12.0
Provides-Extra: test
Requires-Dist: pylint; extra == "test"
Dynamic: license-file
